saispec/__init__.py
saispec/base.py
saispec/core.py
saispec/models.py
saispec/specs.py
saispec-0.1.0.dist-info/licenses/LICENSE
saispec-0.1.0.dist-info/METADATA
saispec-0.1.0.dist-info/WHEEL
saispec-0.1.0.dist-info/top_level.txt
saispec-0.1.0.dist-info/RECORD
