Metadata-Version: 2.4
Name: saispec
Version: 0.1.0
Summary: Governance-first runtime for AI agent safety, permissions, and accountability
Author: SaiSpec Labs
License: MIT
Project-URL: Homepage, https://github.com/SaiSpec-Labs/saispec
Project-URL: Repository, https://github.com/SaiSpec-Labs/saispec
Requires-Python: >=3.9
License-File: LICENSE
Dynamic: license-file
